.gitignore
CHANGELOG.md
Makefile
README.md
requirements.txt
setup.py
tox.ini
cvml/__init__.py
cvml.egg-info/PKG-INFO
cvml.egg-info/SOURCES.txt
cvml.egg-info/dependency_links.txt
cvml.egg-info/requires.txt
cvml.egg-info/top_level.txt
cvml/plot/__init__.py
cvml/plot/confusion_matrix.py
cvml/video/__init__.py
cvml/video/stitch_frames.py
docs/Makefile
docs/make.bat
docs/requirements.txt
docs/source/conf.py
docs/source/index.rst
docs/source/plot.rst
docs/source/video.rst